Nsound.py
_Nsound.cp310-win_amd64.pyd
Nsound-0.9.5.dist-info/AUTHORS
Nsound-0.9.5.dist-info/COPYING
Nsound-0.9.5.dist-info/LICENSE
Nsound-0.9.5.dist-info/METADATA
Nsound-0.9.5.dist-info/WHEEL
Nsound-0.9.5.dist-info/top_level.txt
Nsound-0.9.5.dist-info/RECORD
