Metadata-Version: 2.1
Name: Nsound
Version: 0.9.5
Summary: Nsound is a C++ library and Python module for audio synthesis featuring dynamic digital filters. Nsound lets you easily shape waveforms and write to disk or plot them. Nsound aims to be as powerful as Csound but easy to use.
Home-page: https://github.com/weegreenblobbie/nsound
Author: Nick Hilton et al
Author-email: weegreenblobbie2@gmail.com
License: UNKNOWN
Download-URL: http://sourceforge.net/projects/nsound/files/nsound/nsound-0.9.5/nsound-0.9.5.tar.gz/download
Platform: UNKNOWN
Classifier: Development Status :: 5 - Production/Stable
Classifier: Environment :: Console
Classifier: Environment :: MacOS X
Classifier: Environment :: Win32 (MS Windows)
Classifier: Intended Audience :: Developers
Classifier: Intended Audience :: End Users/Desktop
Classifier: Intended Audience :: Science/Research
Classifier: License :: OSI Approved :: GNU General Public License v2 or later (GPLv2+)
Classifier: Natural Language :: English
Classifier: Operating System :: OS Independent
Classifier: Programming Language :: C++
Classifier: Programming Language :: Python :: 3 :: Only
Classifier: Programming Language :: Python :: 3.10
Classifier: Programming Language :: Python :: Implementation :: CPython
Classifier: Topic :: Multimedia :: Sound/Audio :: Analysis
Classifier: Topic :: Multimedia :: Sound/Audio :: Sound Synthesis
Classifier: Topic :: Multimedia :: Sound/Audio
Classifier: Topic :: Scientific/Engineering :: Information Analysis
Classifier: Topic :: Scientific/Engineering :: Mathematics
Classifier: Topic :: Scientific/Engineering
Classifier: Topic :: Software Development :: Libraries :: Python Modules
Classifier: Topic :: Software Development :: Libraries
Requires-Python: >=3.7
License-File: LICENSE
License-File: COPYING
License-File: AUTHORS
